tex_untag/__init__.py
tex_untag/__main__.py
tex_untag/_version.py
tex_untag/tex_untag.py
tex_untag-1.3.0.dist-info/LICENSE
tex_untag-1.3.0.dist-info/METADATA
tex_untag-1.3.0.dist-info/WHEEL
tex_untag-1.3.0.dist-info/entry_points.txt
tex_untag-1.3.0.dist-info/top_level.txt
tex_untag-1.3.0.dist-info/RECORD
