Metadata-Version: 2.1
Name: tex-untag
Version: 1.3.0
Summary: A script for removing all of a given markup tag from a set of TeX files.
Home-page: https://github.com/adam-rumpf/tex-untag
Author: Adam Rumpf
Author-email: arumpf@floridapoly.edu
License: MIT
Project-URL: Source, https://github.com/adam-rumpf/tex-untag
Project-URL: Bug Tracker, https://github.com/adam-rumpf/tex-untag/issues
Keywords: latex,text processing,text editing
Platform: any
Classifier: Programming Language :: Python :: 3.8
Classifier: Programming Language :: Python :: 3.9
Classifier: License :: OSI Approved :: MIT License
Classifier: Operating System :: OS Independent
Classifier: Development Status :: 5 - Production/Stable
Classifier: Topic :: Text Processing :: Markup :: LaTeX
Classifier: Natural Language :: English
Requires-Python: >=3.8
License-File: LICENSE
